Metadata-Version: 1.1
Name: C-Rank
Version: 3
Summary: Extracts Keyphrases from Documents
Home-page: https://github.com/maurodlt/C-Rank
Author: Mauro DL Tosi
Author-email: maurodlt@hotmail.com
License: MIT
Download-URL: https://github.com/user/maurodlt/C-Rank/archive/v_02.tar.gz
Platform: UNKNOWN
Classifier: Programming Language :: Python :: 3
Classifier: License :: OSI Approved :: MIT License
